smdAPI/__init__.py
smdAPI-0.0.1.dist-info/METADATA
smdAPI-0.0.1.dist-info/WHEEL
smdAPI-0.0.1.dist-info/top_level.txt
smdAPI-0.0.1.dist-info/RECORD
