Metadata-Version: 2.1
Name: smdAPI
Version: 0.0.1
Summary: Python wrapper for SMD3 and SMD4 motor drives, providing all aspects of configuration and control for these drives.
Author: Arun Microelectronics Ltd
Author-email: info@arunmicro.com
Project-URL: Arun Microelectronics Ltd, https://arunmicro.com/
Classifier: Programming Language :: Python :: 3
Classifier: License :: OSI Approved :: MIT License
Classifier: Operating System :: Microsoft :: Windows
Requires-Python: >=3.7
